.gitignore
.gitlab-ci.yml
LICENSE
README.rst
core.c
core.h
interface.pxd
interface.pyx
requirements.txt
setup.cfg
setup.py
test_unit.py
sqlite_numpy/__init__.py
sqlite_numpy/asyncio.py
sqlite_numpy/core.pyi
sqlite_numpy.egg-info/PKG-INFO
sqlite_numpy.egg-info/SOURCES.txt
sqlite_numpy.egg-info/dependency_links.txt
sqlite_numpy.egg-info/requires.txt
sqlite_numpy.egg-info/top_level.txt