Metadata-Version: 1.2
Name: sqlite-numpy
Version: 0.1.0
Summary: Fast SQLite to numpy array loader
Home-page: https://gitlab.com/sgrignard/sqlite_numpy
Author: Sébastien Grignard
Author-email: pub@amakaze.org
License: MIT
Platform: UNKNOWN
Classifier: Development Status :: 4 - Beta
Classifier: Intended Audience :: Developers
Classifier: License :: OSI Approved :: MIT License
Classifier: Programming Language :: Python
Classifier: Topic :: Software Development :: Libraries
Requires-Python: >=3.7
